pywebauto/__init__.py
pywebauto/base_actions.py
pywebauto/base_options.py
pywebauto/cookie_manager.py
pywebauto/test_template.py
pywebauto-1.1.0.dist-info/licenses/LICENSE
pywebauto-1.1.0.dist-info/METADATA
pywebauto-1.1.0.dist-info/WHEEL
pywebauto-1.1.0.dist-info/top_level.txt
pywebauto-1.1.0.dist-info/RECORD
