Metadata-Version: 2.4
Name: pywebauto
Version: 1.1.0
Summary: web自动化开发及测试
Home-page: https://github.com/yandifei/pywebauto
Author: yandifei
Author-email: 3058439878@qq.com
License: MIT
Classifier: Programming Language :: Python :: 3
Classifier: Operating System :: Microsoft :: Windows :: Windows 11
Requires-Python: >=3.8
License-File: LICENSE
Requires-Dist: pytest>=8.3.5
Requires-Dist: selenium>=4.27.1
Dynamic: author
Dynamic: author-email
Dynamic: classifier
Dynamic: description
Dynamic: description-content-type
Dynamic: home-page
Dynamic: license
Dynamic: license-file
Dynamic: requires-dist
Dynamic: requires-python
Dynamic: summary
